[
  {
    "brand": "Maria B",
    "category": "Women",
    "name": "3 Piece Unstitched Embroidered Twill Linen Suit",
    "original_price": "15,890",
    "sale_price": "10,290",
    "product_url": "https://www.mariab.pk/products/mpt-2801-a",
    "image_urls": [
      "https://www.mariab.pk/cdn/shop/files/D-1AFront_A_86263b23-42c8-4653-9760-a7c782a1cac3_2400x2400.jpg?v=1764229120",
      "https://www.mariab.pk/cdn/shop/files/D-1ACloseup_G_c284afc0-3839-49d8-bfb6-dfd3e3503fee_2400x2400.jpg?v=1764229120",
      "https://www.mariab.pk/cdn/shop/files/D-1ACloseup_F_02a5f2ec-9af2-4968-a4e9-8591922e26bb_2400x2400.jpg?v=1764229120"
    ],
    "details": [
      "color: Tea Pink",
      "Shirt: Embroidered Twill Linen Front, Dyed Twill Linen Back, Sleeve & Front Side Panels, Embroidered Organza Sleeve Patches, mbroidered Silk Patti",
      "Trouser: Dyed Linen Trouser",
      "Shawl: Printed Wool Shawl"
    ]
  },
  {
    "brand": "Maria B",
    "category": "Women",
    "name": "3 Piece Unstitched Embroidered Twill Linen Suit",
    "original_price": "15,890",
    "sale_price": "10,290",
    "product_url": "https://www.mariab.pk/products/mpt-2801-b",
    "image_urls": [
      "https://www.mariab.pk/cdn/shop/files/D-1BFront_A_f109f62e-8c01-4e4c-ae68-19e6a535aed0_2400x2400.jpg?v=1764229231",
      "https://www.mariab.pk/cdn/shop/files/D-1BCloseup_F_286ebeca-3248-4fa0-a0d1-42a39d5e04ec_2400x2400.jpg?v=1764229231",
      "https://www.mariab.pk/cdn/shop/files/D-1BFront_B_728e26ef-2c9d-464f-80f0-6c2ded13c39e_2400x2400.jpg?v=1764229231"
    ],
    "details": [
      "color: Grey",
      "Shirt: Embroidered Twill Linen Front, Dyed Twill Linen Back, Sleeve & Front Side Panels, Embroidered Organza Sleeve Patches, Embroidered Silk Patti",
      "Trouser: Dyed Linen Trouser",
      "Shawl: Printed Wool Shawl"
    ]
  },
  {
    "brand": "Maria B",
    "category": "Women",
    "name": "3 Piece Unstitched Embroidered Twill Linen Suit",
    "original_price": "17,890",
    "sale_price": "11,290",
    "product_url": "https://www.mariab.pk/products/mpt-2802-b",
    "image_urls": [
      "https://www.mariab.pk/cdn/shop/files/D-2_B_Front_A_2400x2400.jpg?v=1764229437",
      "https://www.mariab.pk/cdn/shop/files/D-2_B_Closeup_F_2400x2400.jpg?v=1764229437",
      "https://www.mariab.pk/cdn/shop/files/D-2_B_Closeup_E_2400x2400.jpg?v=1764229437"
    ],
    "details": [
      "color: Black",
      "Shirt: Embroidered Twill Linen Front & Sleeves, Embroidered Organza Front Patch, Embroidered Organza Patti, Dyed Twill Linen Back",
      "Trouser: Dyed Linen Trouser",
      "Shawl: Printed Wool Shawl"
    ]
  },
  {
    "brand": "Maria B",
    "category": "Women",
    "name": "3 Piece Unstitched Embroidered Twill Linen Suit",
    "original_price": "15,890",
    "sale_price": "10,290",
    "product_url": "https://www.mariab.pk/products/mpt-2803-a",
    "image_urls": [
      "https://www.mariab.pk/cdn/shop/files/D-3AFront_A_65634206-5ed2-47c4-9dd8-282d3c25d0dc_2400x2400.jpg?v=1764229531",
      "https://www.mariab.pk/cdn/shop/files/D-3ACloseup_D_a30667f3-ca52-4aed-8109-50465d99065d_2400x2400.jpg?v=1764229531",
      "https://www.mariab.pk/cdn/shop/files/D-3ACloseup_F_e3096b2d-3c59-4c9b-8055-0095ec15bcc1_2400x2400.jpg?v=1764229531"
    ],
    "details": [
      "color: Mustard",
      "Shirt: Embroidered Twill Linen Front R+L Panels, Embroidered Twill Linen Patti, Dyed Twill Linen Back, Sleeves & Front Side Panels",
      "Trouser: Dyed Linen Trouser",
      "Shawl: Printed Wool Shawl"
    ]
  },
  {
    "brand": "Maria B",
    "category": "Women",
    "name": "3 Piece Unstitched Embroidered Twill Linen Suit",
    "original_price": "15,890",
    "sale_price": "10,290",
    "product_url": "https://www.mariab.pk/products/mpt-2803-b",
    "image_urls": [
      "https://www.mariab.pk/cdn/shop/files/D-3BFront_A_edbd24ae-423e-4356-9961-0408be793d55_2400x2400.jpg?v=1764229610",
      "https://www.mariab.pk/cdn/shop/files/D-3BCloseup_G_70af6340-d24b-455c-8e3e-e636c1f82a86_2400x2400.jpg?v=1764229610",
      "https://www.mariab.pk/cdn/shop/files/D-3BCloseup_D_a6a8ea6f-29b7-4bd3-9431-835cd0d61f7f_2400x2400.jpg?v=1764229610"
    ],
    "details": [
      "color: Blue",
      "Shirt: Embroidered Twill Linen Front R+L Panels, Embroidered Twill Linen Patti, Dyed Twill Linen Back, Sleeves & Front Side Panels",
      "Trouser: Dyed Linen Trouse",
      "Shawl: Printed Wool Shawl"
    ]
  },
  {
    "brand": "Maria B",
    "category": "Women",
    "name": "3 Piece Unstitched Embroidered Twill Linen Suit",
    "original_price": "15,890",
    "sale_price": "10,290",
    "product_url": "https://www.mariab.pk/products/mpt-2804-a",
    "image_urls": [
      "https://www.mariab.pk/cdn/shop/files/D-4AFront_A_31183646-4136-4238-87b5-363c35906dca_2400x2400.jpg?v=1764229711",
      "https://www.mariab.pk/cdn/shop/files/D-4ACloseup_D_8d657324-9a44-476b-8d0b-19fc90ec9c5a_2400x2400.jpg?v=1764229711",
      "https://www.mariab.pk/cdn/shop/files/D-4ACloseup_C_5568fe56-7409-4833-b65e-0c36af726f88_2400x2400.jpg?v=1764229711"
    ],
    "details": [
      "color: Brown",
      "Shirt: Embroidered Twill Linen Center Panel, Embroidered Twill Linen Front R+L Panels, Dyed Linen Back & Sleeves",
      "Trouser: Dyed Linen Trouser",
      "Shawl: Printed Wool Shawl"
    ]
  },
  {
    "brand": "Maria B",
    "category": "Women",
    "name": "3 Piece Unstitched Embroidered Twill Linen Suit",
    "original_price": "15,890",
    "sale_price": "10,290",
    "product_url": "https://www.mariab.pk/products/mpt-2804-b",
    "image_urls": [
      "https://www.mariab.pk/cdn/shop/files/D-4BFront_A_4d4aa10d-85e2-4592-949e-7154f12794c9_2400x2400.jpg?v=1764229778",
      "https://www.mariab.pk/cdn/shop/files/D-4BCloseup_C_0d5893b4-733f-45b9-ab4b-082b8b2cd4d0_2400x2400.jpg?v=1764229778",
      "https://www.mariab.pk/cdn/shop/files/D-4BFront_B_21c549cb-8b69-4edb-9db9-707752423ed5_2400x2400.jpg?v=1764229778"
    ],
    "details": [
      "color: Pink",
      "Shirt: Embroidered Twill Linen Center Panel, Embroidered Twill Linen Front R+L Panels, Dyed Linen Back & Sleeves",
      "Trouser: Dyed Linen Trouse",
      "Shawl: Printed Wool Shawl"
    ]
  },
  {
    "brand": "Maria B",
    "category": "Women",
    "name": "3 Piece Unstitched Embroidered Twill Linen Suit",
    "original_price": "15,890",
    "sale_price": "10,290",
    "product_url": "https://www.mariab.pk/products/mpt-2805-b",
    "image_urls": [
      "https://www.mariab.pk/cdn/shop/files/D-5FrontB_B_2400x2400.jpg?v=1764229905",
      "https://www.mariab.pk/cdn/shop/files/D-5BCloseup_E_8a6b160d-faf4-434f-8794-5e5d9018850a_2400x2400.jpg?v=1764229905",
      "https://www.mariab.pk/cdn/shop/files/D-5BCloseup_D_f96abb32-238d-4261-9634-7575f4f334f5_2400x2400.jpg?v=1764229905"
    ],
    "details": [
      "color: Purple",
      "Shirt: Embroidered Twill Linen Center Panel, Embroidered Twill Linen Front R+L Panels, Embroidered Twill Linen Patti, Dyed Twill Linen Back & Sleeves",
      "Trouser: Dyed Linen Trouse",
      "Shawl: Printed Wool Shawl"
    ]
  },
  {
    "brand": "Maria B",
    "category": "Women",
    "name": "3 Piece Unstitched Embroidered Twill Linen Suit",
    "original_price": "17,490",
    "sale_price": "11,290",
    "product_url": "https://www.mariab.pk/products/mpt-2806-b",
    "image_urls": [
      "https://www.mariab.pk/cdn/shop/files/D-6BFront_A_fd663170-462b-4a5c-b2b7-2bf93f34b6c9_2400x2400.jpg?v=1764230070",
      "https://www.mariab.pk/cdn/shop/files/D-6BCloseup_C_2400x2400.jpg?v=1764230070",
      "https://www.mariab.pk/cdn/shop/files/D-6BCloseup_E_88228944-e0b4-4209-b7a8-be6e5208df91_2400x2400.jpg?v=1764230070"
    ],
    "details": [
      "color: Black",
      "Shirt: Embroidered Twill Linen Center Panel, Embroidered Twill Linen Front R+L Panels, Embroidered Twill Linen Patti, Dyed Twill Linen Back & Sleeves",
      "Trouser: Dyed Linen Trouse",
      "Shawl: Printed Wool Shawl"
    ]
  },
  {
    "brand": "Maria B",
    "category": "Women",
    "name": "3 Piece Unstitched Embroidered Twill Linen Suit",
    "original_price": "14,890",
    "sale_price": "10,290",
    "product_url": "https://www.mariab.pk/products/mpt-2805-a",
    "image_urls": [
      "https://www.mariab.pk/cdn/shop/files/D-5AFront_A_a3cfcb26-4566-4fbb-8689-27c1864cbaba_2400x2400.jpg?v=1764229834",
      "https://www.mariab.pk/cdn/shop/files/D-5ASide_B_0ba33612-8ea0-4dd1-be4c-1a869bbaacee_2400x2400.jpg?v=1764229834",
      "https://www.mariab.pk/cdn/shop/files/D-5ACloseup_D_a92a9fd8-79ec-400a-bb92-d4ac9bf57f13_2400x2400.jpg?v=1764229834"
    ],
    "details": [
      "color: Maroon",
      "Shirt: Embroidered Twill Linen Center Panel, Embroidered Twill Linen Front R+L Panels, Embroidered Twill Linen Patti, Dyed Twill Linen Back & Sleeves",
      "Trouser: Embroidered Linen Trouser",
      "Shawl: Printed Wool Shawl"
    ]
  },
  {
    "brand": "Maria B",
    "category": "Women",
    "name": "3 Piece Embroidered Slub Khaddar Suit",
    "original_price": "8,890",
    "sale_price": "6,990",
    "product_url": "https://www.mariab.pk/products/mkd-w25-11-black",
    "image_urls": [
      "https://www.mariab.pk/cdn/shop/files/MKDW2511Front_A_2400x2400.jpg?v=1756895623",
      "https://www.mariab.pk/cdn/shop/files/MKDW2511Closeup_D_2400x2400.jpg?v=1756895623",
      "https://www.mariab.pk/cdn/shop/files/MKDW2511Closeup_E_2400x2400.jpg?v=1756895623"
    ],
    "details": [
      "color: Black",
      "Shirt: Straight-Cut Shirt, Embroidered Neckline With Buttons Detailing, Embroidered Side Seams, Embroidered Round Hem, Straight Sleeves With Embroidered Armhole & Border, Fit: Regular, Color: Black, Fabric: Slub Khaddar",
      "Shalwar: Printed Shalwar, Elasticated Waistband, Fit: Regular, Color: Black, Fabric: Slub Khaddar",
      "Dupatta: Dyed Dupatta, Color: Black, Fabric: Chiffon, Work Details: Sequin & Thread Embroidery, Model is wearing 6-8 size"
    ]
  },
  {
    "brand": "Maria B",
    "category": "girls",
    "name": "3 Piece Embroidered Cotton Silk Suit",
    "original_price": "18,890",
    "sale_price": "13,990",
    "product_url": "https://www.mariab.pk/products/mks-w25-16-blue",
    "image_urls": [
      "https://www.mariab.pk/cdn/shop/files/MKSW2516Front_A_2400x2400.jpg?v=1756820074",
      "https://www.mariab.pk/cdn/shop/files/MKSW2516Closeup_E_2400x2400.jpg?v=1756820074",
      "https://www.mariab.pk/cdn/shop/files/MKSW2516Closeup_F_2400x2400.jpg?v=1756820074"
    ],
    "details": [
      "color: Blue",
      "Shirt: Embroidered Neckline With Keyhole & Loop-Button Detailing, Embroidered Bodice, Spray Embroidered Flare, Embroidered Side Open Seams With Tassels Detailing, Gotta Lace & Pleat Detailing On Border, Embroidered Sleeves, Fit: Regular, Color: Blue, Fabric: Cotton Silk",
      "Shalwar: Dyed Dhaka Trouser, Elasticated Waistband, Gotta Lace Detailing On Border, Fit: Regular, Color: Blue, Fabric: Raw Silk",
      "Dupatta: Dyed Dupatta, Two-Side Kiran Lace Border, Color: Blue, Fabric: Chiffon, Work Details: Sequins, Tilla & Thread Embroidery, Model is wearing 6-8 size"
    ]
  },
  {
    "brand": "Maria B",
    "category": "girls",
    "name": "3 Piece Embroidered Cotton Silk Suit",
    "original_price": "17,890",
    "sale_price": "13,990",
    "product_url": "https://www.mariab.pk/products/mks-w25-16-pink",
    "image_urls": [
      "https://www.mariab.pk/cdn/shop/files/MKSW2516PinkFront_A_2400x2400.jpg?v=1756820009",
      "https://www.mariab.pk/cdn/shop/files/MKSW2516PinkCloseup_D_2400x2400.jpg?v=1756820009",
      "https://www.mariab.pk/cdn/shop/files/MKSW2516PinkCloseup_E_2400x2400.jpg?v=1756820009"
    ],
    "details": [
      "color: Pink",
      "Shirt: Embroidered Neckline With Keyhole & Loop-Button Detailing, Embroidered Bodice, Spray Embroidered Flare, Embroidered Side Open Seams With Tassels Detailing, Gotta Lace & Pleat Detailing On Border, Embroidered Sleeves, Fit: Regular, Color: Pink, Fabric: Cotton Silk",
      "Shalwar: Dyed Dhaka Trouser, Elasticated Waistband, Gotta Lace Detailing On Border, Fit: Regular, Color: Pink, Fabric: Raw Silk",
      "Dupatta: Dyed Dupatta, Two-Side Kiran Lace Border, Color: Pink, Fabric: Chiffon, Work Details: Sequins, Tilla & Thread Embroidery, Model is wearing 6-8 size"
    ]
  },
  {
    "brand": "Maria B",
    "category": "girls",
    "name": "3 Piece Embroidered Organza Suit",
    "original_price": "20,780",
    "sale_price": "16,990",
    "product_url": "https://www.mariab.pk/products/mks-w25-22-sea-green",
    "image_urls": [
      "https://www.mariab.pk/cdn/shop/files/MKSW2522Front_A_2400x2400.jpg?v=1756895344",
      "https://www.mariab.pk/cdn/shop/files/MKSW2522Closeup_E_2400x2400.jpg?v=1756895344",
      "https://www.mariab.pk/cdn/shop/files/MKSW2522Closeup_F_2400x2400.jpg?v=1756895344"
    ],
    "details": [
      "color: Sea Green",
      "Shirt: Embroidered Choli, Round Neckline With Pearls Detailing, Gotta Lace Detailing On Border, Puffed Sleeves With Gotta Lace Embroidered Border, Dyed Resham Cotton Lining (Attached), Fit: Regular, Color: Sea Green, Fabric: Organza",
      "Lehenga: Dyed Lehenga With Embroidered Border, Elasticated Waistband, Gotta Lace Detailing On Panels, Dyed Resham Cotton Lining (Attached), Fit: Regular, Color: Sea Green, Fabric: Organza",
      "Dupatta: Dyed Dupatta, Four-Side Lace Border, Color: Sea Green, Fabric: Chiffon, Work Details: Sequins & Thread Embroidery, Model is wearing 6-8 size"
    ]
  },
  {
    "brand": "Maria B",
    "category": "girls",
    "name": "3 Piece Embroidered Organza Suit",
    "original_price": "16,890",
    "sale_price": "12,990",
    "product_url": "https://www.mariab.pk/products/mks-w25-24-blue",
    "image_urls": [
      "https://www.mariab.pk/cdn/shop/files/MKSW2524Front_A_2400x2400.jpg?v=1756895301",
      "https://www.mariab.pk/cdn/shop/files/MKSW2524Closeup_E_2400x2400.jpg?v=1756895301",
      "https://www.mariab.pk/cdn/shop/files/MKSW2524Closeup_F_2400x2400.jpg?v=1756895301"
    ],
    "details": [
      "color: Blue",
      "Frock: Embroidered Neckline With Pearls Drop Detailing, Embroidered Border On Panels, Embroidered Border, Straight Sleeves With Embroidered Border, Dyed Resham Cotton Lining (Attached), Fit: Regular, Color: Blue, Fabric: Organza",
      "Trouser: Dyed Straight Trouser, Elasticated Waistband, Embroidered Border, Fit: Regular, Color: Blue, Fabric: Raw Silk",
      "Dupatta: Dyed Dupatta, Four-Side Gotta Lace Border, Color: Blue, Fabric: Chiffon, Work Details: Sequins & Thread Embroidery, Model is wearing 6-8 size"
    ]
  },
  {
    "brand": "Maria B",
    "category": "girls",
    "name": "3 Piece Embroidered Raw Silk Suit",
    "original_price": "14,870",
    "sale_price": "10,990",
    "product_url": "https://www.mariab.pk/products/mks-w25-26-green",
    "image_urls": [
      "https://www.mariab.pk/cdn/shop/files/MKSW2526GreenFront_A_2400x2400.jpg?v=1757405954",
      "https://www.mariab.pk/cdn/shop/files/MKSW2526GreenCloseup_E_2400x2400.jpg?v=1757405954",
      "https://www.mariab.pk/cdn/shop/files/MKSW2526GreenCloseup_F_2400x2400.jpg?v=1757405954"
    ],
    "details": [
      "color: Green",
      "Shirt: Spray Embroidered Shirt, Embroidered Neckline With Cutout Detailing, Embroidered Border, Straight Embroidered Sleeves, Gotta Balls Drop Detailing On Sleeves & Border, Fit: Regular, Color: Green, Fabric: Raw Silk",
      "Gharara: Screen Printed Gharara, Elasticated Waistband, Gotta Lace Border, Fit: Regular, Color: Green, Fabric: Raw Silk",
      "Dupatta: Dyed Dupatta, Two-Side Kiran Lace Border, Color: Green, Fabric: Chiffon, Work Details: Sequins, Tilla & Thread Embroidery, Model is wearing 6-8 size"
    ]
  },
  {
    "brand": "Maria B",
    "category": "girls",
    "name": "3 Piece Embroidered Silk Net Suit",
    "original_price": "21,980",
    "sale_price": "16,990",
    "product_url": "https://www.mariab.pk/products/mks-w25-08-magenta",
    "image_urls": [
      "https://www.mariab.pk/cdn/shop/files/MKSW2508Front_A_2400x2400.jpg?v=1758197705",
      "https://www.mariab.pk/cdn/shop/files/MKSW2508Side_B_2400x2400.jpg?v=1758197705",
      "https://www.mariab.pk/cdn/shop/files/MKSW2508Closeup_D_2400x2400.jpg?v=1758197705"
    ],
    "details": [
      "color: Megenta",
      "Choli: Spray Embroidered Choli, Embroidered Round Neckline, Embroidered Border, Embroidered Armhole, Straight Sleeves With Embroidered Border, Gotta Balls Drop Detailing On Border & Sleeves, Dyed Sleeveless Resham Cotton Lining (Attached), Fit: Regular, Color: Megenta, Fabric: Silk Net",
      "Lehenga: Screen Printed Lehenga, Gotta Lace Detailing On Panels, Elasticated Waistband, Jacquard Border With Gotta Detailing, Dyed Resham Cotton Lining (Attached), Fit: Regular, Color: Megenta, Fabric: Silk Net",
      "Dupatta: Dyed Dupatta, Two-Side Gotta Lace Border, Dupatta with kiran lace, Color: Blue & Magenta, Fabric: Chiffon, Work Details: Sequins, Tilla & Thread Embroidery, Model is wearing 6-8 size"
    ]
  },
  {
    "brand": "Maria B",
    "category": "boys",
    "name": "2 Piece Embroidered Cotton Suit",
    "original_price": "7,590",
    "sale_price": "6,490",
    "product_url": "https://www.mariab.pk/products/mbk-2p25-01-navy",
    "image_urls": [
      "https://www.mariab.pk/cdn/shop/files/MBK-2P25-01NAVYFront_B_2400x2400.jpg?v=1767600999",
      "https://www.mariab.pk/cdn/shop/files/MBK-2P25-01NAVYFront_A_2400x2400.jpg?v=1767600999",
      "https://www.mariab.pk/cdn/shop/files/MBK-2P25-01MidBlueSide_C_2400x2400.jpg?v=1767600999"
    ],
    "details": [
      "color: Blue",
      "Kurta: Heavy Embroidered Band Collar Neckline, One Side Pocket, Straight Hem, Open Sleeves With Loop Buttons",
      "Shalwar: Dyed Shalwar, Color: Mid Blue, Fit: Regular, Wear Type: Formal, Fabric: Cotton"
    ]
  },
  {
    "brand": "Maria B",
    "category": "boys",
    "name": "2 Piece Blemded Khaddar Suit",
    "original_price": "11,880",
    "sale_price": "8,990",
    "product_url": "https://www.mariab.pk/products/mbk-2pw25-21-umber-brown",
    "image_urls": [
      "https://www.mariab.pk/cdn/shop/files/MBK-2PW25-21UmberBrownFront_A_2400x2400.jpg?v=1764758027",
      "https://www.mariab.pk/cdn/shop/files/MBK-2PW25-21UmberBrownCloseup_B_2400x2400.jpg?v=1764758027",
      "https://www.mariab.pk/cdn/shop/files/MBK-2PW25-21UmberBrownFront_A_2400x2400.jpg?v=1764758027"
    ],
    "details": [
      "color: Brown",
      "Kurta: Band Collar Neckline, Hidden Placket With Embroidery, One Side Pocket, Straight Hem, Embroidered Open Sleeves With Loop-Button Detailing, Embroidered Back Yoke",
      "Shalwar: Dyed Shalwar, Color: Umber Brown, Fit: Regular, Wear Type: Festive, Fabric: Blended Khaddar, Model is wearing medium size"
    ]
  },
  {
    "brand": "Maria B",
    "category": "boys",
    "name": "Natural Karandi Waistcoat",
    "original_price": "13,880",
    "sale_price": "9,990",
    "product_url": "https://www.mariab.pk/products/mbk-wcw25-26-natural",
    "image_urls": [
      "https://www.mariab.pk/cdn/shop/files/MBK-WCW25-26NaturalFront_A_2400x2400.jpg?v=1763625858",
      "https://www.mariab.pk/cdn/shop/files/MBK-WCW25-26NaturalCloseup_C_2400x2400.jpg?v=1763625858",
      "https://www.mariab.pk/cdn/shop/files/MBK-WCW25-26NaturalCloseup_D_2400x2400.jpg?v=1763625858"
    ],
    "details": [
      "Round Band Collar Neck With Button Detailing, Cover Placket, 2 Front Round Patch Pockets, Round Hem, Silk Lining, Color: Natural, Fit: Regular, Wear Type: Formal, Fabric: Karandi, Model is wearing medium size"
    ]
  },
  {
    "brand": "Maria B",
    "category": "boys",
    "name": "Embroidered Blended Kurta",
    "original_price": "7,280",
    "sale_price": "5,490",
    "product_url": "https://www.mariab.pk/products/mbk-krw25-24-chocolate",
    "image_urls": [
      "https://www.mariab.pk/cdn/shop/files/MBK-KRW25-24ChocolateFront_A_2400x2400.jpg?v=1762942922",
      "https://www.mariab.pk/cdn/shop/files/MBK-KRW25-24ChocolateCloseup_D_2400x2400.jpg?v=1762942922",
      "https://www.mariab.pk/cdn/shop/files/MBK-KRW25-24ChocolateCloseup_E_2400x2400.jpg?v=1762942922"
    ],
    "details": [
      "Embroidered Neckline, One Side Pocket, Straight Sleeves With Loop-Button Detailing, Color: Chocolate Brown, Fit: Regular, Wear Type: Formal, Fabric: Blended, Model is wearing medium size, Note: Dry Clean Only"
    ]
  },
  {
    "brand": "Maria B",
    "category": "boys",
    "name": "2 Piece Blemded Khaddar Suit",
    "original_price": "13,890",
    "sale_price": "8,990",
    "product_url": "https://www.mariab.pk/products/mbk-2pw25-20-evening-blue",
    "image_urls": [
      "https://www.mariab.pk/cdn/shop/files/MBK-2PW25-20EveningBlueFront_A_2400x2400.jpg?v=1762344080",
      "https://www.mariab.pk/cdn/shop/files/MBK-2PW25-20EveningBlueCloseup_D_2400x2400.jpg?v=1762344080",
      "https://www.mariab.pk/cdn/shop/files/MBK-2PW25-20EveningBlueCloseup_E_2400x2400.jpg?v=1762344080"
    ],
    "details": [
      "color: Blue",
      "Kurta: Band Collar Neckline, Embroidered Front, One Side Pocket, Straight Hem, Open Sleeves With Embroidered Border & Loop-Button Detailing",
      "Shalwar: Dyed Shalwar, Color: Maroon, Fit: Regular, Wear Type: Festive, Fabric: Blended Khaddar, Model is wearing medium size"
    ]
  },
  {
    "brand": "Maria B",
    "category": "boys",
    "name": "2 Piece Embroidered Cotton Suit",
    "original_price": "8,790",
    "sale_price": "6,490",
    "product_url": "https://www.mariab.pk/products/mbk-2p25-02-off-white",
    "image_urls": [
      "https://www.mariab.pk/cdn/shop/files/MBK-2P25-02WhiteFront_A_2400x2400.jpg?v=1743154508",
      "https://www.mariab.pk/cdn/shop/files/MBK-2P25-02WhiteCloseup_D_2400x2400.jpg?v=1743154508",
      "https://www.mariab.pk/cdn/shop/files/MBK-2P25-02WhiteSide_B_2400x2400.jpg?v=1743154508"
    ],
    "details": [
      "color: White",
      "Kurta: Straight Band Collar Neckline With Embroidered Placket, One Side Pocket, Straight Hem, Open Sleeves With Loop Buttons",
      "Shalwar: Dyed Shalwar, Color: White, Fit: Regular, Wear Type: Formal, Fabric: Cotton"
    ]
  },
  {
    "brand": "Maria B",
    "category": "boys",
    "name": "2 Piece Blended Khaddar Suit",
    "original_price": "12,870",
    "sale_price": "8,990",
    "product_url": "https://www.mariab.pk/products/mbk-2pw25-22-forest-green",
    "image_urls": [
      "https://www.mariab.pk/cdn/shop/files/MBK-2PW25-22ForestGreenFront_A_2400x2400.jpg?v=1762943049",
      "https://www.mariab.pk/cdn/shop/files/MBK-2PW25-22ForestGreenCloseup_D_2400x2400.jpg?v=1762943049",
      "https://www.mariab.pk/cdn/shop/files/MBK-2PW25-22ForestGreenCloseup_E_2400x2400.jpg?v=1762943049"
    ],
    "details": [
      "color: Green",
      "Kurta: Band Collar Neckline, Embroidered Front, One Side Pocket, Straight Hem, Open Sleeves With Loop-Button Detailing",
      "Shalwar: Dyed Shalwar, Color: Forest Green,, Fit: Regular, Wear Type: Festive, Fabric: Blended Khaddar, Model is wearing medium size, Note: Dry Clean Only"
    ]
  },
  {
    "brand": "Maria B",
    "category": "boys",
    "name": "3 Piece Printed Blended Suit",
    "original_price": "15,990",
    "sale_price": "8,860",
    "product_url": "https://www.mariab.pk/products/mbi-3p25-03-purple",
    "image_urls": [
      "https://www.mariab.pk/cdn/shop/files/MBI-3P25-03PurpleFront_A_2_2400x2400.jpg?v=1742461816",
      "https://www.mariab.pk/cdn/shop/files/MBI-3P25-03PurpleCloseup_D_2400x2400.jpg?v=1742461816",
      "https://www.mariab.pk/cdn/shop/files/MBI-3P25-03PurpleFront_A_1_2400x2400.jpg?v=1742461816"
    ],
    "details": [
      "color: Purple",
      "Kurta: Dyed Kurta With Cut & Sew Detail On Front",
      "Shalwar: Dyed Shalwar",
      "WaistCoat: Dyed Printed Waistcoat With Two Flap Pockets, Color: Purple, Fit: Regular, Wear Type: Formal, Fabric: Blended"
    ]
  },
  {
    "brand": "Maria B",
    "category": "men",
    "name": "2 Piece Cotton Suit",
    "original_price": "16,880",
    "sale_price": "10,490",
    "product_url": "https://www.mariab.pk/products/mbms-2p25-04-off-white",
    "image_urls": [
      "https://www.mariab.pk/cdn/shop/files/MBMS-2P25-04EggWhiteFront_A_2400x2400.jpg?v=1741361553",
      "https://www.mariab.pk/cdn/shop/files/MBMS-2P25-04EggWhiteFront_A_2_2400x2400.jpg?v=1741361553",
      "https://www.mariab.pk/cdn/shop/files/MBMS-2P25-04EggWhiteSide_B_2400x2400.jpg?v=1741361553"
    ],
    "details": [
      "color: off white",
      "Kurta: Collar Neckline With Straight Placket, Front Pocket, One Side Pocket, Straight Hem, Sleeves With Cut Cuff, Back Yoke Cut Detail",
      "Shalwar: Dyed Shalwar, Color: Off White, Fit: Regular, Wear Type: Formal, Fabric: Premium Cotton, Model is wearing medium size, Note: Dry Clean Only"
    ]
  },
  {
    "brand": "Maria B",
    "category": "men",
    "name": "2 Piece Blended Suit",
    "original_price": "15,990",
    "sale_price": "10,490",
    "product_url": "https://www.mariab.pk/products/mbms-2p25-08-graphite",
    "image_urls": [
      "https://www.mariab.pk/cdn/shop/files/MBMS-2P25-08GraphiteFront_A_1_2400x2400.jpg?v=1741695360",
      "https://www.mariab.pk/cdn/shop/files/MBMS-2P25-08GraphiteCloseup_B_2400x2400.jpg?v=1741695360",
      "https://www.mariab.pk/cdn/shop/files/MBMS-2P25-08GraphiteCloseup_D_2400x2400.jpg?v=1741695360"
    ],
    "details": [
      "color: Graphite",
      "Kurta: Notch collar With Cut & Sew Detail, Cover Placket, One Side Pocket, Round Hem, Cut & Sew Detail On Cuff",
      "Shalwar: Dyed Shalwar, Color: Graphite, Fit: Regular, Wear Type: Casual, Fabric: Blended, Model is wearing medium size, Note: Dry Clean Only"
    ]
  },
  {
    "brand": "Maria B",
    "category": "men",
    "name": "2 Piece Blended Suit",
    "original_price": "15,990",
    "sale_price": "10,490",
    "product_url": "https://www.mariab.pk/products/mbms-2p25-07-chocolate-brown",
    "image_urls": [
      "https://www.mariab.pk/cdn/shop/files/MBMS-2P25-07ChocolateBrownFront_A_1_2400x2400.jpg?v=1741258995",
      "https://www.mariab.pk/cdn/shop/files/MBMS-2P25-07ChocolateBrownSide_B_2400x2400.jpg?v=1741264150",
      "https://www.mariab.pk/cdn/shop/files/MBMS-2P25-07ChocolateBrownFront_A_2_2400x2400.jpg?v=1741264150"
    ],
    "details": [
      "color: Brown",
      "Kurta: Band Collar With Cut & Sew Detail Placket, Front Patch Pocket With Bone, One Side Pocket, Straight Hem, Cuff Sleeves",
      "Shalwar: Dyed Shalwar, Color: Chocolate Brown, Fit: Regular, Wear Type: Formal, Fabric: Blended, Model is wearing medium size, Note: Dry Clean Only"
    ]
  },
  {
    "brand": "Maria B",
    "category": "men",
    "name": "2 Piece Embroidered Blended Suit",
    "original_price": "15,990",
    "sale_price": "10,490",
    "product_url": "https://www.mariab.pk/products/mbms-2p25-06-smoke-grey",
    "image_urls": [
      "https://www.mariab.pk/cdn/shop/files/MBMS-2P25-06MidBlueFront_A_2400x2400.jpg?v=1744633019",
      "https://www.mariab.pk/cdn/shop/files/MBMS-2P25-06MidBlueCloseup_E_2400x2400.jpg?v=1744633019",
      "https://www.mariab.pk/cdn/shop/files/MBMS-2P25-06MidBlueCloseup_D_2400x2400.jpg?v=1744633019"
    ],
    "details": [
      "color: Grey",
      "Kurta: Collar Neck With Placket & Embroidery, One Side Pocket, Straight Hem, Cuff Sleeves",
      "Shalwar: Dyed Shalwar, Color: Smoke Grey, Fit: Regular, Wear Type: Formal, Fabric: Blended, Model is wearing medium size, Note: Dry Clean Only"
    ]
  },
  {
    "brand": "Maria B",
    "category": "men",
    "name": "Natural Karandi Waistcoat",
    "original_price": "20,880",
    "sale_price": "15,490",
    "product_url": "https://www.mariab.pk/products/mbm-wc25-04-natural",
    "image_urls": [
      "https://www.mariab.pk/cdn/shop/files/MBM-WC25-04_OffWhite_Front_A_2400x2400.jpg?v=1741339360",
      "https://www.mariab.pk/cdn/shop/files/MBM-WC25-04_OffWhite_Closeup_C_2400x2400.jpg?v=1741339360",
      "https://www.mariab.pk/cdn/shop/files/MBM-WC25-04_OffWhite_Side_B_1_2400x2400.jpg?v=1741339360"
    ],
    "details": [
      "Round Band Collar Neck, Classic Buttons On Front, Three Round Patch Pockets With Saddle Stitch, Signature Pin On Front, Round Hem, Self Lining, Color: Natural, Fit: Regular, Wear Type: Formal, Fabric: Karandi, Model is wearing medium size, Note: Dry Clean Only"
    ]
  },
  {
    "brand": "Maria B",
    "category": "men",
    "name": "2 Piece Blended Khaddar Suit",
    "original_price": "18,980",
    "sale_price": "14,990",
    "product_url": "https://www.mariab.pk/products/mbm-2pw25-04-evening-blue",
    "image_urls": [
      "https://www.mariab.pk/cdn/shop/files/MBM-2PW25-04_Evening_Blue_Front_A_2400x2400.jpg?v=1764313860",
      "https://www.mariab.pk/cdn/shop/files/MBM-2PW25-04_Evening_Blue_Closeup_C_2400x2400.jpg?v=1764313860",
      "https://www.mariab.pk/cdn/shop/files/MBM-2PW25-04_Evening_Blue_Closeup_D_2400x2400.jpg?v=1764313860"
    ],
    "details": [
      "color: Blue",
      "Kurta: Band Collar Neckline, Embroidered Front, One Side Pocket, Straight Hem, Open Sleeves With Embroidered Border & Loop-Button Detailing",
      "Shalwar: Dyed Shalwar, Color: Evening Blue, Fit: Regular, Wear Type: Festive, Fabric: Blended Khaddar Model is wearing mediu"
    ]
  },
  {
    "brand": "Maria B",
    "category": "men",
    "name": "Embroidered Jacquard Kurta",
    "original_price": "6,900",
    "sale_price": "4,990",
    "product_url": "https://www.mariab.pk/products/mbm-kr25-09-rust-orange",
    "image_urls": [
      "https://www.mariab.pk/cdn/shop/files/MBM-KR25-09RustOrangeFront_A_2400x2400.jpg?v=1741950997",
      "https://www.mariab.pk/cdn/shop/files/MBM-KR25-09RustOrangeFrontg_2_2400x2400.jpg?v=1741950997",
      "https://www.mariab.pk/cdn/shop/files/MBM-KR25-09RustOrangeCloseup_D_2400x2400.jpg?v=1741950997"
    ],
    "details": [
      "Straight Band Collar, Straight Placket With Embroidery, One Side Pocket, Straight Hem, Open Sleeves With Embroidery & Loop Button Detailing, Color: Rust Orange, Fit: Regular, Wear Type: Formal, Fabric: Signature Jacquard, Model is wearing medium size, Note: Dry Clean Only"
    ]
  }
]
